gemini/__init__.py
gemini/camera.py
gemini/input.py
gemini/utils.py
gemini_engine-1.1.3.dist-info/LICENSE
gemini_engine-1.1.3.dist-info/METADATA
gemini_engine-1.1.3.dist-info/WHEEL
gemini_engine-1.1.3.dist-info/top_level.txt
gemini_engine-1.1.3.dist-info/RECORD
