Metadata-Version: 2.1
Name: gemini-engine
Version: 1.1.3
Summary: A monospace 2D ASCII rendering engine
Home-page: https://github.com/redpenguinyt/GeminiEngine
Author: RedPenguin
Author-email: timmyterskov@gmail.com
Project-URL: Examples, https://github.com/redpenguinyt/GeminiExamples
Project-URL: Bug Tracker, https://github.com/redpenguinyt/GeminiEngine/issues
Classifier: Programming Language :: Python :: 3
Classifier: License :: OSI Approved :: MIT License
Classifier: Operating System :: OS Independent
Requires-Python: >=3.10
License-File: LICENSE
